streamlit_ldap_authenticator/__init__.py
streamlit_ldap_authenticator/authenticate.py
streamlit_ldap_authenticator/configs.py
streamlit_ldap_authenticator/exceptions.py
streamlit_ldap_authenticator/ldap_authenticate.py
streamlit_ldap_authenticator-0.2.6.dist-info/LICENSE
streamlit_ldap_authenticator-0.2.6.dist-info/METADATA
streamlit_ldap_authenticator-0.2.6.dist-info/WHEEL
streamlit_ldap_authenticator-0.2.6.dist-info/top_level.txt
streamlit_ldap_authenticator-0.2.6.dist-info/RECORD
